atlassian/__init__.py
atlassian/bitbucket.py
atlassian/client.py
atlassian/confluence.py
atlassian/error.py
atlassian/jira.py
atlassian/logger.py
atlassian_api_py-0.6.1.dist-info/licenses/LICENSE
atlassian_api_py-0.6.1.dist-info/METADATA
atlassian_api_py-0.6.1.dist-info/WHEEL
atlassian_api_py-0.6.1.dist-info/top_level.txt
atlassian_api_py-0.6.1.dist-info/RECORD
